evrim/__init__.py
evrim/_base_client.py
evrim/_client.py
evrim/_compat.py
evrim/_constants.py
evrim/_exceptions.py
evrim/_files.py
evrim/_models.py
evrim/_qs.py
evrim/_resource.py
evrim/_response.py
evrim/_streaming.py
evrim/_types.py
evrim/_version.py
evrim/py.typed
evrim/_utils/__init__.py
evrim/_utils/_logs.py
evrim/_utils/_proxy.py
evrim/_utils/_reflection.py
evrim/_utils/_streams.py
evrim/_utils/_sync.py
evrim/_utils/_transform.py
evrim/_utils/_typing.py
evrim/_utils/_utils.py
evrim/lib/.keep
evrim/resources/__init__.py
evrim/resources/collections.py
evrim/resources/created_fields.py
evrim/resources/fields.py
evrim/resources/prompt_templates.py
evrim/resources/snapshots.py
evrim/resources/blank/__init__.py
evrim/resources/blank/blank.py
evrim/resources/blank/profiles.py
evrim/resources/blank/templates.py
evrim/resources/bulk/__init__.py
evrim/resources/bulk/bulk.py
evrim/resources/bulk/collections/__init__.py
evrim/resources/bulk/collections/collections.py
evrim/resources/bulk/collections/profiles.py
evrim/resources/bulk/templates/__init__.py
evrim/resources/bulk/templates/profiles.py
evrim/resources/bulk/templates/templates.py
evrim/resources/prod/__init__.py
evrim/resources/prod/prod.py
evrim/resources/prod/v0/__init__.py
evrim/resources/prod/v0/answers.py
evrim/resources/prod/v0/v0.py
evrim/resources/prod/v0/compose/__init__.py
evrim/resources/prod/v0/compose/compose.py
evrim/resources/prod/v0/compose/profile.py
evrim/resources/prod/v0/costs/__init__.py
evrim/resources/prod/v0/costs/answer.py
evrim/resources/prod/v0/costs/costs.py
evrim/resources/prod/v0/costs/created_field.py
evrim/resources/prod/v0/costs/average/__init__.py
evrim/resources/prod/v0/costs/average/average.py
evrim/resources/prod/v0/costs/average/field.py
evrim/resources/prod/v0/extract/__init__.py
evrim/resources/prod/v0/extract/command.py
evrim/resources/prod/v0/extract/extract.py
evrim/resources/prod/v0/extract/raw.py
evrim/resources/prod/v0/extract/relationship.py
evrim-2.8.0.dist-info/METADATA
evrim-2.8.0.dist-info/WHEEL
evrim-2.8.0.dist-info/licenses/LICENSE
evrim-2.8.0.dist-info/RECORD
